apigateway/__init__.py
apigateway/__version__.py
apigateway/auth.py
tencentcloud_apigateway_authorization-0.1.0.dist-info/METADATA
tencentcloud_apigateway_authorization-0.1.0.dist-info/RECORD
tencentcloud_apigateway_authorization-0.1.0.dist-info/WHEEL
tencentcloud_apigateway_authorization-0.1.0.dist-info/top_level.txt
