Metadata-Version: 2.1
Name: tencentcloud-apigateway-authorization
Version: 0.1.0
Summary: Generate headers with authorization for the request of TencentCloud Apigateway API.
Home-page: https://github.com/duyixian1234/tencentcloud-apigateway-authorization
Author: Yixian Du
Author-email: duyixian1234@qq.com
License: MIT
Platform: UNKNOWN
Classifier: License :: OSI Approved :: MIT License
Classifier: Programming Language :: Python
Classifier: Programming Language :: Python :: 3.6
Classifier: Programming Language :: Python :: Implementation :: CPython
Classifier: Programming Language :: Python :: Implementation :: PyPy
